garages_burgos/__init__.py
garages_burgos-1.1.2.dist-info/METADATA
garages_burgos-1.1.2.dist-info/WHEEL
garages_burgos-1.1.2.dist-info/RECORD
