Metadata-Version: 2.1
Name: garages-burgos
Version: 1.1.2
Summary: Asynchronous Python client for getting garage occupancy in Burgos
Home-page: https://github.com/ricveal/garages_burgos
License: MIT
Keywords: garages,burgos,occupancy,api,async,client
Author: ricveal
Author-email: ricveal@gmail.com
Requires-Python: >=3.7,<4.0
Classifier: Framework :: AsyncIO
Classifier: Intended Audience :: Developers
Classifier: License :: OSI Approved :: MIT License
Classifier: Natural Language :: English
Classifier: Programming Language :: Python :: 3
Classifier: Programming Language :: Python :: 3.7
Classifier: Programming Language :: Python :: 3.8
Classifier: Programming Language :: Python :: 3.9
Classifier: Programming Language :: Python :: 3.10
Classifier: Programming Language :: Python :: 3.11
Classifier: Programming Language :: Python :: 3
Classifier: Programming Language :: Python :: 3.7
Classifier: Programming Language :: Python :: 3.8
Classifier: Programming Language :: Python :: 3.9
Classifier: Topic :: Software Development :: Libraries :: Python Modules
Requires-Dist: aiohttp (>=3.0.0,<4.0.0)
Project-URL: Repository, https://github.com/ricveal/garages_burgos
